hey/__init__.py
hey/cli.py
hey/consts.py
hey/editor.py
hey/exceptions.py
hey/openai.py
hey/configs/__init__.py
hey/configs/cli.py
hey/configs/utils.py
hey_mindsdb-0.4.0.dist-info/METADATA
hey_mindsdb-0.4.0.dist-info/WHEEL
hey_mindsdb-0.4.0.dist-info/entry_points.txt
hey_mindsdb-0.4.0.dist-info/licenses/LICENSE
hey_mindsdb-0.4.0.dist-info/RECORD
