Metadata-Version: 2.3
Name: hey_mindsdb
Version: 0.4.0
Summary: Your AI-powered pair programming friend
Project-URL: Repository, https://github.com/lnxpy/hey
Author-email: Sadra Yahyapour <lnxpylnxpy@gmail.com>
License: MIT License
License-File: LICENSE
Classifier: Development Status :: 5 - Production/Stable
Classifier: Environment :: Console
Classifier: Intended Audience :: Developers
Classifier: License :: OSI Approved :: MIT License
Classifier: Operating System :: OS Independent
Classifier: Programming Language :: Python
Classifier: Programming Language :: Python :: 3 :: Only
Classifier: Programming Language :: Python :: 3.8
Classifier: Programming Language :: Python :: 3.9
Classifier: Programming Language :: Python :: 3.10
Classifier: Programming Language :: Python :: 3.11
Classifier: Programming Language :: Python :: 3.12
Requires-Python: >=3.8
Requires-Dist: keyring>=25.3.0
Requires-Dist: openai>=1.30.1
Requires-Dist: platformdirs>=4.2.2
Requires-Dist: rich>=13.7.1
Requires-Dist: typer>=0.12.3
Provides-Extra: dev
Requires-Dist: coverage; extra == 'dev'
Requires-Dist: pytest-cookies; extra == 'dev'
